Branching/__init__.py
Branching/main.py
branching-1.1.1.dist-info/WHEEL
branching-1.1.1.dist-info/METADATA
branching-1.1.1.dist-info/RECORD
