Metadata-Version: 2.1
Name: branching
Version: 1.1.1
Summary: A Framework That Provides Easy To Use Plugin Integration.
Author: InEase
Author-email: InEase28@gmail.com
Requires-Python: >=3.8,<4.0
Classifier: Programming Language :: Python :: 3
Classifier: Programming Language :: Python :: 3.8
Classifier: Programming Language :: Python :: 3.9
Classifier: Programming Language :: Python :: 3.10
Classifier: Programming Language :: Python :: 3.11
